gen_gender/__init__.py
gen_gender/main.py
gen_gender/pkl/bin_dict_noun_female.pkl
gen_gender/pkl/bin_dict_noun_male.pkl
gen_gender/pkl/dict.opcorpora.pkl
gen_gender/pkl/not_correct.pkl
gen_gender/pkl/not_correct_lemma.pkl
gen_gender/txt/dict.opcorpora.txt
gen_gender/txt/fem_name.txt
gen_gender/txt/itogovy_slovar.txt
gen_gender/txt/masc_name.txt
gen_gender/txt/non_correct.txt
gen_gender/txt/not_correct.txt
gen_gender-0.1.4.dist-info/METADATA
gen_gender-0.1.4.dist-info/WHEEL
gen_gender-0.1.4.dist-info/RECORD
