Metadata-Version: 2.1
Name: gen-gender
Version: 0.1.4
Summary: Изменение рода ответа с мужского на женский
Home-page: https://git.promo-bot.ru/v.merkurev/gen_gender
Keywords: promo-bot,promobot
Author: vmerkurev
Author-email: v.merkurev@promo-bot.ru
Maintainer: VMerkurev
Maintainer-email: v.merkurev@promo-bot.ru
Requires-Python: >=3.8,<4.0
Classifier: Programming Language :: Python :: 3
Classifier: Programming Language :: Python :: 3.8
Classifier: Programming Language :: Python :: 3.9
Classifier: Programming Language :: Python :: 3.10
Classifier: Programming Language :: Python :: 3.11
Requires-Dist: stanza (>=1.4.2,<2.0.0)
Project-URL: Repository, https://git.promo-bot.ru/v.merkurev/gen_gender
